zxing/__init__.py
zxing/__main__.py
zxing/version.py
zxing/java/core.jar
zxing/java/javase.jar
zxing/java/jcommander.jar
zxingmod-0.19.dist-info/LICENSE
zxingmod-0.19.dist-info/METADATA
zxingmod-0.19.dist-info/WHEEL
zxingmod-0.19.dist-info/entry_points.txt
zxingmod-0.19.dist-info/top_level.txt
zxingmod-0.19.dist-info/RECORD
